py3make/__init__.py
py3make/__main__.py
py3make/_main.py
py3make/_pymake.py
py3make/_utils.py
py3make/_version.py
py3make-1.0.4.dist-info/LICENCE
py3make-1.0.4.dist-info/METADATA
py3make-1.0.4.dist-info/WHEEL
py3make-1.0.4.dist-info/entry_points.txt
py3make-1.0.4.dist-info/top_level.txt
py3make-1.0.4.dist-info/RECORD
