Metadata-Version: 2.1
Name: py3make
Version: 1.0.4
Summary: Makefile execution powered by pure Python
Author-email: Stephen Karl Larroque <LRQ3000@gmail.com>, Casper da Costa-Luis <casper.dcl@physics.org>
Maintainer-email: tqdm developers <python.tqdm@gmail.com>
License: MIT License
Project-URL: Homepage, https://github.com/lrq3000/py3make
Project-URL: Documentation, https://github.com/lrq3000/py3make/blob/master/README.md
Project-URL: Source, https://github.com/lrq3000/py3make
Project-URL: Tracker, https://github.com/lrq3000/py3make/issues
Project-URL: Download, https://github.com/lrq3000/py3make/releases
Project-URL: Changelog, https://allmychanges.com/p/python/py3make/
Keywords: make,makefile,gnumake,gnu,console,terminal,cli,py3make,pymake,py-make
Classifier: Development Status :: 5 - Production/Stable
Classifier: License :: OSI Approved :: MIT License
Classifier: Environment :: Console
Classifier: Operating System :: MacOS :: MacOS X
Classifier: Operating System :: Microsoft :: Windows
Classifier: Operating System :: POSIX
Classifier: Operating System :: POSIX :: BSD
Classifier: Operating System :: POSIX :: BSD :: FreeBSD
Classifier: Operating System :: POSIX :: Linux
Classifier: Operating System :: POSIX :: SunOS/Solaris
Classifier: Intended Audience :: Developers
Classifier: Intended Audience :: System Administrators
Classifier: Programming Language :: Python
Classifier: Programming Language :: Python :: 3
Classifier: Programming Language :: Python :: 3.7
Classifier: Programming Language :: Python :: 3.8
Classifier: Programming Language :: Python :: 3.9
Classifier: Programming Language :: Python :: 3.10
Classifier: Programming Language :: Python :: 3.11
Classifier: Programming Language :: Python :: 3.12
Classifier: Programming Language :: Python :: Implementation :: PyPy
Classifier: Topic :: Software Development :: Build Tools
Classifier: Topic :: Software Development :: Libraries
Classifier: Topic :: Software Development :: Libraries :: Python Modules
Classifier: Topic :: Software Development :: Pre-processors
Classifier: Topic :: Software Development :: User Interfaces
Classifier: Topic :: System :: Installation/Setup
Classifier: Topic :: System :: Logging
Classifier: Topic :: System :: Monitoring
Classifier: Topic :: System :: Shells
Classifier: Topic :: Terminals
Classifier: Topic :: Utilities
Requires-Python: >=3.7
License-File: LICENCE
Requires-Dist: docopt (>=0.6.0)
Provides-Extra: test
Requires-Dist: pytest ; extra == 'test'
Requires-Dist: pytest-cov ; extra == 'test'
Requires-Dist: coveralls ; extra == 'test'
Requires-Dist: flake8 ; extra == 'test'
Requires-Dist: Flake8-pyproject ; extra == 'test'
Provides-Extra: testmeta
Requires-Dist: build ; extra == 'testmeta'
Requires-Dist: twine ; extra == 'testmeta'
Requires-Dist: validate-pyproject ; extra == 'testmeta'
Requires-Dist: rstcheck ; extra == 'testmeta'
